kraken_datatype/__init__.py
kraken_datatype/_datatype_address.py
kraken_datatype/_datatype_bool.py
kraken_datatype/_datatype_city.py
kraken_datatype/_datatype_country.py
kraken_datatype/_datatype_currency.py
kraken_datatype/_datatype_data.py
kraken_datatype/_datatype_datatype.py
kraken_datatype/_datatype_date.py
kraken_datatype/_datatype_domain.py
kraken_datatype/_datatype_email.py
kraken_datatype/_datatype_organization.py
kraken_datatype/_datatype_state.py
kraken_datatype/_datatype_telephone.py
kraken_datatype/_datatype_text.py
kraken_datatype/_datatype_url.py
kraken_datatype/_datatype_zipcode.py
kraken_datatype/_guess_engine.py
kraken_datatype/_main_processor.py
kraken_datatype/kraken_datatype.py
kraken_datatype-0.0.14.dist-info/LICENSE.txt
kraken_datatype-0.0.14.dist-info/METADATA
kraken_datatype-0.0.14.dist-info/WHEEL
kraken_datatype-0.0.14.dist-info/top_level.txt
kraken_datatype-0.0.14.dist-info/RECORD
