Metadata-Version: 2.1
Name: kraken-datatype
Version: 0.0.14
Summary: Kraken datatype
Home-page: https://github.com/tactik8/kraken_datatype2
Author: Tactik8
Author-email: info@tactik8.com
License: MIT
Classifier: License :: OSI Approved :: MIT License
Classifier: Programming Language :: Python :: 3
Classifier: Programming Language :: Python :: 3.8
License-File: LICENSE.txt
Requires-Dist: url-normalize
Requires-Dist: validators
Requires-Dist: dateparser
Requires-Dist: pycountry
Requires-Dist: email-normalize
Requires-Dist: cleanco
Requires-Dist: phonenumbers
Requires-Dist: google-i18n-address
